pySTTM/setup.py
pySTTM-0.1.1.dist-info/METADATA
pySTTM-0.1.1.dist-info/WHEEL
pySTTM-0.1.1.dist-info/top_level.txt
pySTTM-0.1.1.dist-info/RECORD
